Workbook

Sheet RISK_DASHBOARD
A1: Meridian Credit Fund I — Risk Dashboard
A2: As of Q1 2026 | All figures in USD unless stated | Source: PRIVATECREDIT.PUBLIC (Snowflake)
A4: A. Portfolio Risk Scorecard
A5: Total Committed ($) | G5: Total Fair Value ($) | M5: # Active Loans
A6: =SUM(LOAN_DATA!K3:K7) -> 62500000 | G6: =SUM(LOAN_DATA!L3:L7) -> 64650000 | M6: =COUNTIF(LOAN_DATA!AC3:AC7,"Active")+COUNTIF(LOAN_DATA!AC3:AC7,"Extended") -> 3
A8: Avg LTV | G8: Avg DSCR | M8: # Covenant Breaches
A9: =AVERAGEIF(LOAN_DATA!K3:K7,">0",LOAN_DATA!S3:S7) -> 0.566 | G9: =AVERAGEIF(LOAN_DATA!K3:K7,">0",LOAN_DATA!T3:T7) -> 1.694 | M9: =COUNTIF(LOAN_DATA!U3:U7,"Breach Risk")+COUNTIF(LOAN_DATA!U3:U7,"Monitoring") -> 2
A11: Annual Cash Income ($) | G11: Wtd Avg Int Rate | M11: Wtd Avg All-In Yield
A12: =SUM(LOAN_DATA!AJ3:AJ7) -> 8945000 | G12: =SUMPRODUCT(LOAN_DATA!K3:K7,LOAN_DATA!M3:M7)/SUM(LOAN_DATA!K3:K7) -> 0.12776 | M12: =SUMPRODUCT(LOAN_DATA!K3:K7,LOAN_DATA!AI3:AI7)/SUM(LOAN_DATA!K3:K7) -> 0.14839733
A15: B. Exposure by Sector
A16: Sector | B16: # Loans | C16: Principal ($) | D16: Fair Value ($) | E16: % of Portfolio | F16: Avg LTV | G16: Avg DSCR | H16: Risk Limit | I16: Status
A17: Energy | B17: =COUNTIF(LOAN_DATA!E3:E7,A17) -> 1 | C17: =SUMIF(LOAN_DATA!E3:E7,A17,LOAN_DATA!K3:K7) -> 11000000 | D17: =SUMIF(LOAN_DATA!E3:E7,A17,LOAN_DATA!L3:L7) -> 11400000 | E17: =IFERROR(LOAN_DATA!L6/SUM(LOAN_DATA!L3:L7),0) -> 0.17633411 | F17: =IFERROR(AVERAGEIF(LOAN_DATA!E3:E7,A17,LOAN_DATA!S3:S7),"-") -> 0.68 | G17: =IFERROR(AVERAGEIF(LOAN_DATA!E3:E7,A17,LOAN_DATA!T3:T7),"-") -> 1.32 | H17: 0.2 | I17: =IF(D17/SUM(LOAN_DATA!L3:L7)*100>20,"BREACH","Compliant") -> Compliant
A18: Healthcare | B18: =COUNTIF(LOAN_DATA!E3:E7,A18) -> 1 | C18: =SUMIF(LOAN_DATA!E3:E7,A18,LOAN_DATA!K3:K7) -> 6000000 | D18: =SUMIF(LOAN_DATA!E3:E7,A18,LOAN_DATA!L3:L7) -> 6150000 | E18: =IFERROR(LOAN_DATA!L7/SUM(LOAN_DATA!L3:L7),0) -> 0.09512761 | F18: =IFERROR(AVERAGEIF(LOAN_DATA!E3:E7,A18,LOAN_DATA!S3:S7),"-") -> 0.5 | G18: =IFERROR(AVERAGEIF(LOAN_DATA!E3:E7,A18,LOAN_DATA!T3:T7),"-") -> 1.95 | H18: 0.3 | I18: =IF(D18/SUM(LOAN_DATA!L3:L7)*100>30,"BREACH","Compliant") -> Compliant
A19: Industrials | B19: =COUNTIF(LOAN_DATA!E3:E7,A19) -> 1 | C19: =SUMIF(LOAN_DATA!E3:E7,A19,LOAN_DATA!K3:K7) -> 15000000 | D19: =SUMIF(LOAN_DATA!E3:E7,A19,LOAN_DATA!L3:L7) -> 15800000 | E19: =IFERROR(LOAN_DATA!L3/SUM(LOAN_DATA!L3:L7),0) -> 0.24439288 | F19: =IFERROR(AVERAGEIF(LOAN_DATA!E3:E7,A19,LOAN_DATA!S3:S7),"-") -> 0.55 | G19: =IFERROR(AVERAGEIF(LOAN_DATA!E3:E7,A19,LOAN_DATA!T3:T7),"-") -> 1.82 | H19: 0.3 | I19: =IF(D19/SUM(LOAN_DATA!L3:L7)*100>30,"BREACH","Compliant") -> Compliant
A20: Retail | B20: =COUNTIF(LOAN_DATA!E3:E7,A20) -> 1 | C20: =SUMIF(LOAN_DATA!E3:E7,A20,LOAN_DATA!K3:K7) -> 8500000 | D20: =SUMIF(LOAN_DATA!E3:E7,A20,LOAN_DATA!L3:L7) -> 8200000 | E20: =IFERROR(LOAN_DATA!L4/SUM(LOAN_DATA!L3:L7),0) -> 0.12683681 | F20: =IFERROR(AVERAGEIF(LOAN_DATA!E3:E7,A20,LOAN_DATA!S3:S7),"-") -> 0.62 | G20: =IFERROR(AVERAGEIF(LOAN_DATA!E3:E7,A20,LOAN_DATA!T3:T7),"-") -> 1.28 | H20: 0.2 | I20: =IF(D20/SUM(LOAN_DATA!L3:L7)*100>20,"BREACH","Compliant") -> Compliant
A21: Technology | B21: =COUNTIF(LOAN_DATA!E3:E7,A21) -> 1 | C21: =SUMIF(LOAN_DATA!E3:E7,A21,LOAN_DATA!K3:K7) -> 22000000 | D21: =SUMIF(LOAN_DATA!E3:E7,A21,LOAN_DATA!L3:L7) -> 23100000 | E21: =IFERROR(LOAN_DATA!L5/SUM(LOAN_DATA!L3:L7),0) -> 0.35730858 | F21: =IFERROR(AVERAGEIF(LOAN_DATA!E3:E7,A21,LOAN_DATA!S3:S7),"-") -> 0.48 | G21: =IFERROR(AVERAGEIF(LOAN_DATA!E3:E7,A21,LOAN_DATA!T3:T7),"-") -> 2.1 | H21: 0.3 | I21: =IF(D21/SUM(LOAN_DATA!L3:L7)*100>30,"BREACH","Compliant") -> BREACH
A22: TOTAL | B22: =SUM(B17:B21) -> 5 | C22: =SUM(C17:C21) -> 62500000 | D22: =SUM(D17:D21) -> 64650000 | E22: =SUM(E17:E21) -> 1
A23: =SUM(LOAN_DATA!L3:L7) -> 64650000
A24: C. Covenant & Loan Status Monitor
A25: Security ID | B25: Borrower | C25: Sector | D25: Loan Status | E25: Covenant Status | F25: LTV | G25: LTV Limit | H25: LTV Headroom | I25: DSCR | J25: DSCR Floor | K25: DSCR Headroom | L25: Days to Maturity | M25: Action Required
A26: =LOAN_DATA!A3 -> PC001 | B26: =LOAN_DATA!D3 -> Apex Manufacturing Co | C26: =LOAN_DATA!E3 -> Industrials | D26: =LOAN_DATA!AC3 -> Active | E26: =LOAN_DATA!U3 -> Compliant | F26: =LOAN_DATA!S3 -> 0.55 | G26: 0.75 | H26: =G26-F26 -> 0.2 | I26: =LOAN_DATA!T3 -> 1.82 | J26: 1.25 | K26: =I26-J26 -> 0.57 | L26: =IFERROR(LOAN_DATA!AH3,"") -> 198 | M26: =IF(E26="Breach Risk","⚠ Covenant breach — waiver required",IF(E26="Monitoring","⚠ Monitoring — below revenue covenant",IF(H26<0,"⚠ LTV breach",IF(K26<0,"⚠ DSCR below floor",IF(L26<90,"Approaching maturity","OK"))))) -> OK
A27: =LOAN_DATA!A4 -> PC002 | B27: =LOAN_DATA!D4 -> Sunset Retail Group | C27: =LOAN_DATA!E4 -> Retail | D27: =LOAN_DATA!AC4 -> Matured-Pending | E27: =LOAN_DATA!U4 -> Monitoring | F27: =LOAN_DATA!S4 -> 0.62 | G27: 0.75 | H27: =G27-F27 -> 0.13 | I27: =LOAN_DATA!T4 -> 1.28 | J27: 1.2 | K27: =I27-J27 -> 0.08 | L27: =IFERROR(LOAN_DATA!AH4,"") -> -30 | M27: =IF(E27="Breach Risk","⚠ Covenant breach — waiver required",IF(E27="Monitoring","⚠ Monitoring — below revenue covenant",IF(H27<0,"⚠ LTV breach",IF(K27<0,"⚠ DSCR below floor",IF(L27<90,"Approaching maturity","OK"))))) -> ⚠ Monitoring — below revenue covenant
A28: =LOAN_DATA!A5 -> PC003 | B28: =LOAN_DATA!D5 -> TechCo Holdings | C28: =LOAN_DATA!E5 -> Technology | D28: =LOAN_DATA!AC5 -> Extended | E28: =LOAN_DATA!U5 -> Compliant | F28: =LOAN_DATA!S5 -> 0.48 | G28: 0.65 | H28: =G28-F28 -> 0.17 | I28: =LOAN_DATA!T5 -> 2.1 | J28: 1.25 | K28: =I28-J28 -> 0.85 | L28: =IFERROR(LOAN_DATA!AH5,"") -> 184 | M28: =IF(E28="Breach Risk","⚠ Covenant breach — waiver required",IF(E28="Monitoring","⚠ Monitoring — below revenue covenant",IF(H28<0,"⚠ LTV breach",IF(K28<0,"⚠ DSCR below floor",IF(L28<90,"Approaching maturity","OK"))))) -> OK
A29: =LOAN_DATA!A6 -> PC004 | B29: =LOAN_DATA!D6 -> GreenEnergy GmbH | C29: =LOAN_DATA!E6 -> Energy | D29: =LOAN_DATA!AC6 -> Watch-list | E29: =LOAN_DATA!U6 -> Breach Risk | F29: =LOAN_DATA!S6 -> 0.68 | G29: 0.75 | H29: =G29-F29 -> 0.07 | I29: =LOAN_DATA!T6 -> 1.32 | J29: 1.5 | K29: =I29-J29 -> -0.18 | L29: =IFERROR(LOAN_DATA!AH6,"") -> 427 | M29: =IF(E29="Breach Risk","⚠ Covenant breach — waiver required",IF(E29="Monitoring","⚠ Monitoring — below revenue covenant",IF(H29<0,"⚠ LTV breach",IF(K29<0,"⚠ DSCR below floor",IF(L29<90,"Approaching maturity","OK"))))) -> ⚠ Covenant breach — waiver required
A30: =LOAN_DATA!A7 -> PC005 | B30: =LOAN_DATA!D7 -> MedSupply Corp | C30: =LOAN_DATA!E7 -> Healthcare | D30: =LOAN_DATA!AC7 -> Active | E30: =LOAN_DATA!U7 -> Compliant | F30: =LOAN_DATA!S7 -> 0.5 | G30: 0.7 | H30: =G30-F30 -> 0.2 | I30: =LOAN_DATA!T7 -> 1.95 | J30: 1.25 | K30: =I30-J30 -> 0.7 | L30: =IFERROR(LOAN_DATA!AH7,"") -> 123 | M30: =IF(E30="Breach Risk","⚠ Covenant breach — waiver required",IF(E30="Monitoring","⚠ Monitoring — below revenue covenant",IF(H30<0,"⚠ LTV breach",IF(K30<0,"⚠ DSCR below floor",IF(L30<90,"Approaching maturity","OK"))))) -> OK

Sheet EXPOSURE_ANALYSIS
A1: Meridian Credit Fund I — Exposure Analysis
A2: Portfolio concentration, geography, and collateral breakdown | Source: PRIVATECREDIT.PUBLIC
A4: A. Loan-Level Exposure Summary
A5: Security ID | B5: Borrower | C5: Sector | D5: Geography | E5: Principal ($) | F5: Fair Value ($) | G5: % NAV | H5: LTV | I5: DSCR | J5: Rate | K5: PIK | L5: All-In Yield | M5: Annual Income ($) | N5: Loan Status | O5: Covenant
A6: =LOAN_DATA!A3 -> PC001 | B6: =LOAN_DATA!D3 -> Apex Manufacturing Co | C6: =LOAN_DATA!E3 -> Industrials | D6: =LOAN_DATA!F3 -> USA | E6: =LOAN_DATA!K3 -> 15000000 | F6: =LOAN_DATA!L3 -> 15800000 | G6: =IFERROR(F6/SUM($F$6:$F$10),0) -> 0.24439288 | H6: =LOAN_DATA!S3 -> 0.55 | I6: =LOAN_DATA!T3 -> 1.82 | J6: =LOAN_DATA!M3 -> 0.125 | K6: =LOAN_DATA!N3 -> 0.02 | L6: =LOAN_DATA!AI3 -> 0.15 | M6: =LOAN_DATA!AJ3 -> 2175000 | N6: =LOAN_DATA!AC3 -> Active | O6: =LOAN_DATA!U3 -> Compliant
A7: =LOAN_DATA!A4 -> PC002 | B7: =LOAN_DATA!D4 -> Sunset Retail Group | C7: =LOAN_DATA!E4 -> Retail | D7: =LOAN_DATA!F4 -> UK | E7: =LOAN_DATA!K4 -> 8500000 | F7: =LOAN_DATA!L4 -> 8200000 | G7: =IFERROR(F7/SUM($F$6:$F$10),0) -> 0.12683681 | H7: =LOAN_DATA!S4 -> 0.62 | I7: =LOAN_DATA!T4 -> 1.28 | J7: =LOAN_DATA!M4 -> 0.13 | K7: =LOAN_DATA!N4 -> 0 | L7: =LOAN_DATA!AI4 -> 0.13833333 | M7: =LOAN_DATA!AJ4 -> 1105000 | N7: =LOAN_DATA!AC4 -> Matured-Pending | O7: =LOAN_DATA!U4 -> Monitoring
A8: =LOAN_DATA!A5 -> PC003 | B8: =LOAN_DATA!D5 -> TechCo Holdings | C8: =LOAN_DATA!E5 -> Technology | D8: =LOAN_DATA!F5 -> USA | E8: =LOAN_DATA!K5 -> 22000000 | F8: =LOAN_DATA!L5 -> 23100000 | G8: =IFERROR(F8/SUM($F$6:$F$10),0) -> 0.35730858 | H8: =LOAN_DATA!S5 -> 0.48 | I8: =LOAN_DATA!T5 -> 2.1 | J8: =LOAN_DATA!M5 -> 0.14 | K8: =LOAN_DATA!N5 -> 0.03 | L8: =LOAN_DATA!AI5 -> 0.175 | M8: =LOAN_DATA!AJ5 -> 3740000 | N8: =LOAN_DATA!AC5 -> Extended | O8: =LOAN_DATA!U5 -> Compliant
A9: =LOAN_DATA!A6 -> PC004 | B9: =LOAN_DATA!D6 -> GreenEnergy GmbH | C9: =LOAN_DATA!E6 -> Energy | D9: =LOAN_DATA!F6 -> Germany | E9: =LOAN_DATA!K6 -> 11000000 | F9: =LOAN_DATA!L6 -> 11400000 | G9: =IFERROR(F9/SUM($F$6:$F$10),0) -> 0.17633411 | H9: =LOAN_DATA!S6 -> 0.68 | I9: =LOAN_DATA!T6 -> 1.32 | J9: =LOAN_DATA!M6 -> 0.115 | K9: =LOAN_DATA!N6 -> 0 | L9: =LOAN_DATA!AI6 -> 0.119 | M9: =LOAN_DATA!AJ6 -> 1265000 | N9: =LOAN_DATA!AC6 -> Watch-list | O9: =LOAN_DATA!U6 -> Breach Risk
A10: =LOAN_DATA!A7 -> PC005 | B10: =LOAN_DATA!D7 -> MedSupply Corp | C10: =LOAN_DATA!E7 -> Healthcare | D10: =LOAN_DATA!F7 -> Canada | E10: =LOAN_DATA!K7 -> 6000000 | F10: =LOAN_DATA!L7 -> 6150000 | G10: =IFERROR(F10/SUM($F$6:$F$10),0) -> 0.09512761 | H10: =LOAN_DATA!S7 -> 0.5 | I10: =LOAN_DATA!T7 -> 1.95 | J10: =LOAN_DATA!M7 -> 0.11 | K10: =LOAN_DATA!N7 -> 0 | L10: =LOAN_DATA!AI7 -> 0.115 | M10: =LOAN_DATA!AJ7 -> 660000 | N10: =LOAN_DATA!AC7 -> Active | O10: =LOAN_DATA!U7 -> Compliant
A11: TOTAL / WTD AVG | E11: =SUM(E6:E10) -> 62500000 | F11: =SUM(F6:F10) -> 64650000 | G11: =SUM(G6:G10) -> 1 | H11: =SUMPRODUCT(E6:E10,H6:H10)/SUM(E6:E10) -> 0.55296 | I11: =SUMPRODUCT(E6:E10,I6:I10)/SUM(E6:E10) -> 1.7696 | J11: =SUMPRODUCT(E6:E10,J6:J10)/SUM(E6:E10) -> 0.12776 | L11: =SUMPRODUCT(E6:E10,L6:L10)/SUM(E6:E10) -> 0.14839733 | M11: =SUM(M6:M10) -> 8945000
A13: B. Geography Breakdown
A14: Geography | B14: # Loans | C14: Principal ($) | D14: Fair Value ($) | E14: % Portfolio | F14: Avg LTV | G14: Avg DSCR | H14: CCY
A15: USA | B15: =COUNTIF(LOAN_DATA!F3:F7,A15) -> 2 | C15: =SUMIF(LOAN_DATA!F3:F7,A15,LOAN_DATA!K3:K7) -> 37000000 | D15: =SUMIF(LOAN_DATA!F3:F7,A15,LOAN_DATA!L3:L7) -> 38900000 | E15: =IFERROR(D15/SUM(LOAN_DATA!L3:L7),0) -> 0.60170147 | F15: =IFERROR(AVERAGEIF(LOAN_DATA!F3:F7,A15,LOAN_DATA!S3:S7),"-") -> 0.515 | G15: =IFERROR(AVERAGEIF(LOAN_DATA!F3:F7,A15,LOAN_DATA!T3:T7),"-") -> 1.96 | H15: USD
A16: UK | B16: =COUNTIF(LOAN_DATA!F3:F7,A16) -> 1 | C16: =SUMIF(LOAN_DATA!F3:F7,A16,LOAN_DATA!K3:K7) -> 8500000 | D16: =SUMIF(LOAN_DATA!F3:F7,A16,LOAN_DATA!L3:L7) -> 8200000 | E16: =IFERROR(D16/SUM(LOAN_DATA!L3:L7),0) -> 0.12683681 | F16: =IFERROR(AVERAGEIF(LOAN_DATA!F3:F7,A16,LOAN_DATA!S3:S7),"-") -> 0.62 | G16: =IFERROR(AVERAGEIF(LOAN_DATA!F3:F7,A16,LOAN_DATA!T3:T7),"-") -> 1.28 | H16: GBP
A17: Germany | B17: =COUNTIF(LOAN_DATA!F3:F7,A17) -> 1 | C17: =SUMIF(LOAN_DATA!F3:F7,A17,LOAN_DATA!K3:K7) -> 11000000 | D17: =SUMIF(LOAN_DATA!F3:F7,A17,LOAN_DATA!L3:L7) -> 11400000 | E17: =IFERROR(D17/SUM(LOAN_DATA!L3:L7),0) -> 0.17633411 | F17: =IFERROR(AVERAGEIF(LOAN_DATA!F3:F7,A17,LOAN_DATA!S3:S7),"-") -> 0.68 | G17: =IFERROR(AVERAGEIF(LOAN_DATA!F3:F7,A17,LOAN_DATA!T3:T7),"-") -> 1.32 | H17: EUR
A18: Canada | B18: =COUNTIF(LOAN_DATA!F3:F7,A18) -> 1 | C18: =SUMIF(LOAN_DATA!F3:F7,A18,LOAN_DATA!K3:K7) -> 6000000 | D18: =SUMIF(LOAN_DATA!F3:F7,A18,LOAN_DATA!L3:L7) -> 6150000 | E18: =IFERROR(D18/SUM(LOAN_DATA!L3:L7),0) -> 0.09512761 | F18: =IFERROR(AVERAGEIF(LOAN_DATA!F3:F7,A18,LOAN_DATA!S3:S7),"-") -> 0.5 | G18: =IFERROR(AVERAGEIF(LOAN_DATA!F3:F7,A18,LOAN_DATA!T3:T7),"-") -> 1.95 | H18: CAD
A19: TOTAL | B19: =SUM(B15:B18) -> 5 | C19: =SUM(C15:C18) -> 62500000 | D19: =SUM(D15:D18) -> 64650000 | E19: =SUM(E15:E18) -> 1
A21: C. Collateral Coverage Analysis
A22: Borrower | B22: Collateral Type | C22: Collateral Value ($) | D22: Principal ($) | E22: Coverage Ratio | F22: LTV | G22: Collateral Cushion ($) | H22: Assessment
A23: =LOAN_DATA!D3 -> Apex Manufacturing Co | B23: =LOAN_DATA!V3 -> Plant & Machinery | C23: =LOAN_DATA!W3 -> 18500000 | D23: =LOAN_DATA!K3 -> 15000000 | E23: =IFERROR(C23/D23,0) -> 1.2333333 | F23: =LOAN_DATA!S3 -> 0.55 | G23: =C23-D23 -> 3500000 | H23: =IF(E23>=2,"Strong",IF(E23>=1.5,"Adequate",IF(E23>=1,"Thin","Under-collateralised"))) -> Thin
A24: =LOAN_DATA!D4 -> Sunset Retail Group | B24: =LOAN_DATA!V4 -> Receivables & Inventory | C24: =LOAN_DATA!W4 -> 11200000 | D24: =LOAN_DATA!K4 -> 8500000 | E24: =IFERROR(C24/D24,0) -> 1.3176471 | F24: =LOAN_DATA!S4 -> 0.62 | G24: =C24-D24 -> 2700000 | H24: =IF(E24>=2,"Strong",IF(E24>=1.5,"Adequate",IF(E24>=1,"Thin","Under-collateralised"))) -> Thin
A25: =LOAN_DATA!D5 -> TechCo Holdings | B25: =LOAN_DATA!V5 -> IP & Software | C25: =LOAN_DATA!W5 -> 32000000 | D25: =LOAN_DATA!K5 -> 22000000 | E25: =IFERROR(C25/D25,0) -> 1.4545455 | F25: =LOAN_DATA!S5 -> 0.48 | G25: =C25-D25 -> 10000000 | H25: =IF(E25>=2,"Strong",IF(E25>=1.5,"Adequate",IF(E25>=1,"Thin","Under-collateralised"))) -> Thin
A26: =LOAN_DATA!D6 -> GreenEnergy GmbH | B26: =LOAN_DATA!V6 -> Real Assets | C26: =LOAN_DATA!W6 -> 14800000 | D26: =LOAN_DATA!K6 -> 11000000 | E26: =IFERROR(C26/D26,0) -> 1.3454545 | F26: =LOAN_DATA!S6 -> 0.68 | G26: =C26-D26 -> 3800000 | H26: =IF(E26>=2,"Strong",IF(E26>=1.5,"Adequate",IF(E26>=1,"Thin","Under-collateralised"))) -> Thin
A27: =LOAN_DATA!D7 -> MedSupply Corp | B27: =LOAN_DATA!V7 -> Receivables | C27: =LOAN_DATA!W7 -> 9200000 | D27: =LOAN_DATA!K7 -> 6000000 | E27: =IFERROR(C27/D27,0) -> 1.5333333 | F27: =LOAN_DATA!S7 -> 0.5 | G27: =C27-D27 -> 3200000 | H27: =IF(E27>=2,"Strong",IF(E27>=1.5,"Adequate",IF(E27>=1,"Thin","Under-collateralised"))) -> Adequate

Sheet LOAN_DATA
A1: PRIVATECREDIT.PUBLIC — Meridian Credit Fund I | Loan Master Data (Source: Snowflake PRIVATECREDIT.PUBLIC.PRIVATE_CREDIT + PC_BORROWER_FINANCIALS)
A2: Security ID | B2: Security Name | C2: Fund | D2: Borrower | E2: Sector | F2: Geography | G2: Origination Date | H2: Maturity Date | I2: Tenor (Mo) | J2: IO Period (Mo) | K2: Principal ($) | L2: Current Value ($) | M2: Interest Rate | N2: PIK Rate | O2: Orig Fee | P2: EOT Fee | Q2: Payment Type | R2: Repayment Freq | S2: LTV | T2: DSCR | U2: Covenant Status | V2: Collateral Type | W2: Collateral Value ($) | X2: Borrower Revenue ($) | Y2: Borrower EBITDA ($) | Z2: Borrower Net Debt ($) | AA2: Leverage Ratio | AB2: Interest Coverage | AC2: Loan Status | AD2: Last Payment | AE2: Next Payment | AF2: Total Interest Rcvd ($) | AG2: Total Principal Repaid ($) | AH2: Days to Maturity | AI2: All-In Yield | AJ2: Annual Income ($)
A3: PC001 | B3: Apex Manufacturing Loan | C3: Meridian Credit Fund I | D3: Apex Manufacturing Co | E3: Industrials | F3: USA | G3: 2023-01-15 | H3: 2027-01-15 | I3: 48 | J3: 12 | K3: 15000000 | L3: 15800000 | M3: 0.125 | N3: 0.02 | O3: 0.02 | P3: 0.025 | Q3: Amortizing | R3: Quarterly | S3: 0.55 | T3: 1.82 | U3: Compliant | V3: Plant & Machinery | W3: 18500000 | X3: 82000000 | Y3: 14500000 | Z3: 16200000 | AA3: 1.12 | AB3: 2.18 | AC3: Active | AD3: 2025-10-15 | AE3: 2026-01-15 | AF3: 2175000 | AG3: 3750000 | AH3: =IFERROR(H3-TODAY(),"") -> 198 | AI3: =IFERROR(M3+N3+O3/I3*12,"") -> 0.15 | AJ3: =IFERROR(K3*(M3+N3),"") -> 2175000
A4: PC002 | B4: Sunset Retail Facility | C4: Meridian Credit Fund I | D4: Sunset Retail Group | E4: Retail | F4: UK | G4: 2023-06-01 | H4: 2026-06-01 | I4: 36 | J4: 6 | K4: 8500000 | L4: 8200000 | M4: 0.13 | N4: 0 | O4: 0.025 | P4: 0.03 | Q4: Amortizing | R4: Monthly | S4: 0.62 | T4: 1.28 | U4: Monitoring | V4: Receivables & Inventory | W4: 11200000 | X4: 16400000 | Y4: 3100000 | Z4: 9200000 | AA4: 2.97 | AB4: 1.19 | AC4: Matured-Pending | AD4: 2026-05-01 | AF4: 3315000 | AG4: 7083333 | AH4: =IFERROR(H4-TODAY(),"") -> -30 | AI4: =IFERROR(M4+N4+O4/I4*12,"") -> 0.13833333 | AJ4: =IFERROR(K4*(M4+N4),"") -> 1105000
A5: PC003 | B5: TechCo Bridge Loan | C5: Meridian Credit Fund I | D5: TechCo Holdings | E5: Technology | F5: USA | G5: 2024-01-01 | H5: 2027-01-01 | I5: 36 | J5: 24 | K5: 22000000 | L5: 23100000 | M5: 0.14 | N5: 0.03 | O5: 0.015 | P5: 0.02 | Q5: Bullet | R5: Quarterly | S5: 0.48 | T5: 2.1 | U5: Compliant | V5: IP & Software | W5: 32000000 | X5: 48000000 | Y5: 18500000 | Z5: 24800000 | AA5: 1.34 | AB5: 2.64 | AC5: Extended | AD5: 2026-03-01 | AE5: 2026-06-01 | AF5: 5280000 | AG5: 0 | AH5: =IFERROR(H5-TODAY(),"") -> 184 | AI5: =IFERROR(M5+N5+O5/I5*12,"") -> 0.175 | AJ5: =IFERROR(K5*(M5+N5),"") -> 3740000
A6: PC004 | B6: GreenEnergy Term Loan | C6: Meridian Credit Fund I | D6: GreenEnergy GmbH | E6: Energy | F6: Germany | G6: 2022-09-01 | H6: 2027-09-01 | I6: 60 | J6: 18 | K6: 11000000 | L6: 11400000 | M6: 0.115 | N6: 0 | O6: 0.02 | P6: 0.025 | Q6: Amortizing | R6: Semi-Annual | S6: 0.68 | T6: 1.32 | U6: Breach Risk | V6: Real Assets | W6: 14800000 | X6: 28500000 | Y6: 5800000 | Z6: 13200000 | AA6: 2.28 | AB6: 1.32 | AC6: Watch-list | AD6: 2026-03-01 | AE6: 2026-09-01 | AF6: 2185000 | AG6: 2200000 | AH6: =IFERROR(H6-TODAY(),"") -> 427 | AI6: =IFERROR(M6+N6+O6/I6*12,"") -> 0.119 | AJ6: =IFERROR(K6*(M6+N6),"") -> 1265000
A7: PC005 | B7: MedSupply Revolving Credit | C7: Meridian Credit Fund I | D7: MedSupply Corp | E7: Healthcare | F7: Canada | G7: 2023-11-01 | H7: 2026-11-01 | I7: 36 | J7: 6 | K7: 6000000 | L7: 6150000 | M7: 0.11 | N7: 0 | O7: 0.015 | P7: 0.015 | Q7: Amortizing | R7: Monthly | S7: 0.5 | T7: 1.95 | U7: Compliant | V7: Receivables | W7: 9200000 | X7: 41000000 | Y7: 9800000 | Z7: 6500000 | AA7: 0.66 | AB7: 2.94 | AC7: Active | AD7: 2026-05-01 | AE7: 2026-06-01 | AF7: 1017500 | AG7: 3500000 | AH7: =IFERROR(H7-TODAY(),"") -> 123 | AI7: =IFERROR(M7+N7+O7/I7*12,"") -> 0.115 | AJ7: =IFERROR(K7*(M7+N7),"") -> 660000
A10: FX RATES (Source: PC_FX_RATES — WM/Reuters 4pm London Fix)
A11: Quarter | B11: Rate Date | C11: Currency Pair | D11: Rate to USD | E11: Rate Source
A12: Q1 2026 | B12: 2026-03-31 | C12: GBP/USD | D12: 1.2942 | E12: WM/Reuters
A13: Q1 2026 | B13: 2026-03-31 | C13: EUR/USD | D13: 1.0814 | E13: WM/Reuters
A14: Q1 2026 | B14: 2026-03-31 | C14: CAD/USD | D14: 0.7381 | E14: WM/Reuters
A15: Q4 2025 | B15: 2025-12-31 | C15: GBP/USD | D15: 1.2521 | E15: WM/Reuters
A16: Q4 2025 | B16: 2025-12-31 | C16: EUR/USD | D16: 1.0352 | E16: WM/Reuters
A17: Q4 2025 | B17: 2025-12-31 | C17: CAD/USD | D17: 0.6943 | E17: WM/Reuters
A18: Q3 2025 | B18: 2025-09-30 | C18: GBP/USD | D18: 1.3384 | E18: WM/Reuters
A19: Q3 2025 | B19: 2025-09-30 | C19: EUR/USD | D19: 1.1162 | E19: WM/Reuters
A20: Q3 2025 | B20: 2025-09-30 | C20: CAD/USD | D20: 0.7462 | E20: WM/Reuters

Sheet ASSUMPTIONS
A1: Meridian Credit Fund I — Model Assumptions & Inputs
A3: FUND PARAMETERS
B4: Fund inception date | D4: 2022-06-15
B5: Reporting currency | D5: USD
B6: Total LP commitments ($) | D6: 62500000
B7: GP commitment ($) | D7: 2500000
B8: Fund term (years) | D8: 8
B9: Investment period (years) | D9: 4
B10: Target gross IRR (%) | D10: 0.12
B11: Target net IRR (%) | D11: 0.09
B12: Benchmark | D12: Cliffwater Direct Lending Index
A14: RISK LIMITS
B15: Max single-name exposure (%) | D15: 0.25
B16: Max sector — Technology (%) | D16: 0.3
B17: Max sector — Industrials (%) | D17: 0.3
B18: Max sector — Retail (%) | D18: 0.2
B19: Max sector — Energy (%) | D19: 0.2
B20: Max sector — Healthcare (%) | D20: 0.3
B21: Max geography — Non-USD (%) | D21: 0.4
A23: COVENANT FLOORS
B24: Min DSCR (all loans) | D24: 1.25
B25: Max LTV (standard) | D25: 0.75
B26: Max LTV (Retail) | D26: 0.7
B27: Max LTV (Technology) | D27: 0.65
A29: FEE ASSUMPTIONS
B30: Standard management fee (%) | D30: 0.015
B31: Standard carry (%) | D31: 0.2
B32: Preferred return (hurdle, %) | D32: 0.08
B33: Catch-up (%) | D33: 1
A35: VALUATION
B36: Primary mark methodology | D36: DCF
B37: Discount rate — performing (%) | D37: 0.12
B38: Discount rate — monitoring (%) | D38: 0.15
B39: Discount rate — breach (%) | D39: 0.18

Sheet TIMESERIES
A1: Meridian Credit Fund I — Time-Series Analysis
A2: Quarterly marks, fair value, unrealized G/L, income accrual | Source: PC_MARKS + PC_CASHFLOW
A4: A. Quarterly Fair Value Marks — by Loan
A5: Quarter | B5: Mark Date | C5: Borrower | D5: Sector | E5: Outstanding Principal ($) | F5: Fair Value ($) | G5: Unrealized G/L ($) | H5: Mark-to-Par | I5: DSCR at Mark | J5: LTV at Mark | K5: Covenant Status | L5: Cash Interest Accrued ($) | M5: PIK Interest Accrued ($) | N5: Total Income Accrued ($) | O5: Mark Method
A6: Q1 2023 | B6: 2023-03-31 | C6: Apex Manufacturing Co | D6: Industrials | E6: 15000000 | F6: 15000000 | G6: 0 | H6: 1 | J6: 0.55 | K6: Compliant | L6: 0 | M6: 0 | N6: 0 | O6: Cost
A7: Q2 2023 | B7: 2023-06-30 | C7: Apex Manufacturing Co | D7: Industrials | E7: 15000000 | F7: 15150000 | G7: 150000 | H7: 1.01 | I7: 1.85 | J7: 0.545 | K7: Compliant | L7: 543750 | M7: 75000 | N7: 618750 | O7: DCF
A8: Q3 2023 | B8: 2023-09-30 | C8: Apex Manufacturing Co | D8: Industrials | E8: 15000000 | F8: 15300000 | G8: 300000 | H8: 1.02 | I8: 1.88 | J8: 0.54 | K8: Compliant | L8: 543750 | M8: 75000 | N8: 618750 | O8: DCF
A9: Q4 2023 | B9: 2023-12-31 | C9: Apex Manufacturing Co | D9: Industrials | E9: 14750000 | F9: 14900000 | G9: 150000 | H9: 1.01 | I9: 1.91 | J9: 0.538 | K9: Compliant | L9: 543750 | M9: 75000 | N9: 618750 | O9: DCF
A10: Q4 2023 | B10: 2023-12-31 | C10: Sunset Retail Group | D10: Retail | E10: 8500000 | F10: 8450000 | G10: -50000 | H10: 0.994 | I10: 1.31 | J10: 0.61 | K10: Compliant | L10: 276250 | M10: 0 | N10: 276250 | O10: DCF
A11: Q4 2023 | B11: 2023-12-31 | C11: GreenEnergy GmbH | D11: Energy | E11: 11000000 | F11: 11100000 | G11: 100000 | H11: 1.009 | I11: 1.45 | J11: 0.67 | K11: Compliant | L11: 317500 | M11: 0 | N11: 317500 | O11: DCF
A12: Q1 2024 | B12: 2024-03-31 | C12: Apex Manufacturing Co | D12: Industrials | E12: 14500000 | F12: 14750000 | G12: 250000 | H12: 1.017 | I12: 1.94 | J12: 0.535 | K12: Compliant | L12: 543750 | M12: 75000 | N12: 618750 | O12: DCF
A13: Q1 2024 | B13: 2024-03-31 | C13: Sunset Retail Group | D13: Retail | E13: 8250000 | F13: 8100000 | G13: -150000 | H13: 0.982 | I13: 1.26 | J13: 0.625 | K13: Monitoring | L13: 276250 | M13: 0 | N13: 276250 | O13: DCF
A14: Q1 2024 | B14: 2024-03-31 | C14: GreenEnergy GmbH | D14: Energy | E14: 11000000 | F14: 11050000 | G14: 50000 | H14: 1.005 | I14: 1.41 | J14: 0.674 | K14: Compliant | L14: 317500 | M14: 0 | N14: 317500 | O14: DCF
A15: Q1 2024 | B15: 2024-03-31 | C15: TechCo Holdings | D15: Technology | E15: 22000000 | F15: 22500000 | G15: 500000 | H15: 1.023 | I15: 2.15 | J15: 0.479 | K15: Compliant | L15: 770000 | M15: 660000 | N15: 1430000 | O15: DCF
A16: Q2 2024 | B16: 2024-06-30 | C16: Apex Manufacturing Co | D16: Industrials | E16: 14250000 | F16: 14600000 | G16: 350000 | H16: 1.025 | I16: 1.97 | J16: 0.532 | K16: Compliant | L16: 543750 | M16: 75000 | N16: 618750 | O16: DCF
A17: Q2 2024 | B17: 2024-06-30 | C17: Sunset Retail Group | D17: Retail | E17: 8000000 | F17: 7800000 | G17: -200000 | H17: 0.975 | I17: 1.22 | J17: 0.638 | K17: Monitoring | L17: 276250 | M17: 0 | N17: 276250 | O17: DCF
A18: Q2 2024 | B18: 2024-06-30 | C18: GreenEnergy GmbH | D18: Energy | E18: 11000000 | F18: 10950000 | G18: -50000 | H18: 0.995 | I18: 1.38 | J18: 0.679 | K18: Monitoring | L18: 317500 | M18: 0 | N18: 317500 | O18: DCF
... A35: Q1 2026 | B35: 2026-03-31 | C35: MedSupply Corp | D35: Healthcare | E35: 6000000 | F35: 6150000 | G35: 150000 | H35: 1.025 | I35: 1.95 | J35: 0.5 | K35: Compliant | L35: 165000 | M35: 0 | N35: 165000 | O35: DCF
A38: B. Quarterly Portfolio Roll-Up (Aggregated)
A39: Quarter | B39: Mark Date | C39: # Loans Marked | D39: Total Outstanding ($) | E39: Total Fair Value ($) | F39: Aggregate Unrealized G/L ($) | G39: Wtd Avg Mark-to-Par | H39: Wtd Avg DSCR | I39: Wtd Avg LTV | J39: Total Income Accrued ($) | K39: # Covenant Issues
A40: Q1 2023 | B40: 2023-03-31 | C40: =COUNTIF($A$6:$A$35,A40) -> 1 | D40: =SUMIF($A$6:$A$35,A40,$E$6:$E$35) -> 15000000 | E40: =SUMIF($A$6:$A$35,A40,$F$6:$F$35) -> 15000000 | F40: =SUMIF($A$6:$A$35,A40,$G$6:$G$35) -> 0 | G40: =IFERROR(SUMIF($A$6:$A$35,A40,$F$6:$F$35)/SUMIF($A$6:$A$35,A40,$E$6:$E$35),"") -> 1 | H40: =IFERROR(SUMPRODUCT(($A$6:$A$35=A40)*($I$6:$I$35>0)*$E$6:$E$35*$I$6:$I$35)/SUMPRODUCT(($A$6:$A$35=A40)*($I$6:$I$35>0)*$E$6:$E$35),"") | I40: =IFERROR(SUMPRODUCT(($A$6:$A$35=A40)*$E$6:$E$35*$J$6:$J$35)/SUMIF($A$6:$A$35,A40,$E$6:$E$35),"") -> 0.55 | J40: =SUMIF($A$6:$A$35,A40,$N$6:$N$35) -> 0 | K40: =COUNTIFS($A$6:$A$35,A40,$K$6:$K$35,"Breach Risk")+COUNTIFS($A$6:$A$35,A40,$K$6:$K$35,"Monitoring") -> 0
A41: Q2 2023 | B41: 2023-06-30 | C41: =COUNTIF($A$6:$A$35,A41) -> 1 | D41: =SUMIF($A$6:$A$35,A41,$E$6:$E$35) -> 15000000 | E41: =SUMIF($A$6:$A$35,A41,$F$6:$F$35) -> 15150000 | F41: =SUMIF($A$6:$A$35,A41,$G$6:$G$35) -> 150000 | G41: =IFERROR(SUMIF($A$6:$A$35,A41,$F$6:$F$35)/SUMIF($A$6:$A$35,A41,$E$6:$E$35),"") -> 1.01 | H41: =IFERROR(SUMPRODUCT(($A$6:$A$35=A41)*($I$6:$I$35>0)*$E$6:$E$35*$I$6:$I$35)/SUMPRODUCT(($A$6:$A$35=A41)*($I$6:$I$35>0)*$E$6:$E$35),"") -> 1.85 | I41: =IFERROR(SUMPRODUCT(($A$6:$A$35=A41)*$E$6:$E$35*$J$6:$J$35)/SUMIF($A$6:$A$35,A41,$E$6:$E$35),"") -> 0.545 | J41: =SUMIF($A$6:$A$35,A41,$N$6:$N$35) -> 618750 | K41: =COUNTIFS($A$6:$A$35,A41,$K$6:$K$35,"Breach Risk")+COUNTIFS($A$6:$A$35,A41,$K$6:$K$35,"Monitoring") -> 0
A42: Q3 2023 | B42: 2023-09-30 | C42: =COUNTIF($A$6:$A$35,A42) -> 1 | D42: =SUMIF($A$6:$A$35,A42,$E$6:$E$35) -> 15000000 | E42: =SUMIF($A$6:$A$35,A42,$F$6:$F$35) -> 15300000 | F42: =SUMIF($A$6:$A$35,A42,$G$6:$G$35) -> 300000 | G42: =IFERROR(SUMIF($A$6:$A$35,A42,$F$6:$F$35)/SUMIF($A$6:$A$35,A42,$E$6:$E$35),"") -> 1.02 | H42: =IFERROR(SUMPRODUCT(($A$6:$A$35=A42)*($I$6:$I$35>0)*$E$6:$E$35*$I$6:$I$35)/SUMPRODUCT(($A$6:$A$35=A42)*($I$6:$I$35>0)*$E$6:$E$35),"") -> 1.88 | I42: =IFERROR(SUMPRODUCT(($A$6:$A$35=A42)*$E$6:$E$35*$J$6:$J$35)/SUMIF($A$6:$A$35,A42,$E$6:$E$35),"") -> 0.54 | J42: =SUMIF($A$6:$A$35,A42,$N$6:$N$35) -> 618750 | K42: =COUNTIFS($A$6:$A$35,A42,$K$6:$K$35,"Breach Risk")+COUNTIFS($A$6:$A$35,A42,$K$6:$K$35,"Monitoring") -> 0
A43: Q4 2023 | B43: 2023-12-31 | C43: =COUNTIF($A$6:$A$35,A43) -> 3 | D43: =SUMIF($A$6:$A$35,A43,$E$6:$E$35) -> 34250000 | E43: =SUMIF($A$6:$A$35,A43,$F$6:$F$35) -> 34450000 | F43: =SUMIF($A$6:$A$35,A43,$G$6:$G$35) -> 200000 | G43: =IFERROR(SUMIF($A$6:$A$35,A43,$F$6:$F$35)/SUMIF($A$6:$A$35,A43,$E$6:$E$35),"") -> 1.0058394 | H43: =IFERROR(SUMPRODUCT(($A$6:$A$35=A43)*($I$6:$I$35>0)*$E$6:$E$35*$I$6:$I$35)/SUMPRODUCT(($A$6:$A$35=A43)*($I$6:$I$35>0)*$E$6:$E$35),"") -> 1.6133577 | I43: =IFERROR(SUMPRODUCT(($A$6:$A$35=A43)*$E$6:$E$35*$J$6:$J$35)/SUMIF($A$6:$A$35,A43,$E$6:$E$35),"") -> 0.59826277 | J43: =SUMIF($A$6:$A$35,A43,$N$6:$N$35) -> 1212500 | K43: =COUNTIFS($A$6:$A$35,A43,$K$6:$K$35,"Breach Risk")+COUNTIFS($A$6:$A$35,A43,$K$6:$K$35,"Monitoring") -> 0
A44: Q1 2024 | B44: 2024-03-31 | C44: =COUNTIF($A$6:$A$35,A44) -> 4 | D44: =SUMIF($A$6:$A$35,A44,$E$6:$E$35) -> 55750000 | E44: =SUMIF($A$6:$A$35,A44,$F$6:$F$35) -> 56400000 | F44: =SUMIF($A$6:$A$35,A44,$G$6:$G$35) -> 650000 | G44: =IFERROR(SUMIF($A$6:$A$35,A44,$F$6:$F$35)/SUMIF($A$6:$A$35,A44,$E$6:$E$35),"") -> 1.0116592 | H44: =IFERROR(SUMPRODUCT(($A$6:$A$35=A44)*($I$6:$I$35>0)*$E$6:$E$35*$I$6:$I$35)/SUMPRODUCT(($A$6:$A$35=A44)*($I$6:$I$35>0)*$E$6:$E$35),"") -> 1.8176682 | I44: =IFERROR(SUMPRODUCT(($A$6:$A$35=A44)*$E$6:$E$35*$J$6:$J$35)/SUMIF($A$6:$A$35,A44,$E$6:$E$35),"") -> 0.55364574 | J44: =SUMIF($A$6:$A$35,A44,$N$6:$N$35) -> 2642500 | K44: =COUNTIFS($A$6:$A$35,A44,$K$6:$K$35,"Breach Risk")+COUNTIFS($A$6:$A$35,A44,$K$6:$K$35,"Monitoring") -> 1
A45: Q2 2024 | B45: 2024-06-30 | C45: =COUNTIF($A$6:$A$35,A45) -> 5 | D45: =SUMIF($A$6:$A$35,A45,$E$6:$E$35) -> 61250000 | E45: =SUMIF($A$6:$A$35,A45,$F$6:$F$35) -> 62500000 | F45: =SUMIF($A$6:$A$35,A45,$G$6:$G$35) -> 1250000 | G45: =IFERROR(SUMIF($A$6:$A$35,A45,$F$6:$F$35)/SUMIF($A$6:$A$35,A45,$E$6:$E$35),"") -> 1.0204082 | H45: =IFERROR(SUMPRODUCT(($A$6:$A$35=A45)*($I$6:$I$35>0)*$E$6:$E$35*$I$6:$I$35)/SUMPRODUCT(($A$6:$A$35=A45)*($I$6:$I$35>0)*$E$6:$E$35),"") -> 1.8535918 | I45: =IFERROR(SUMPRODUCT(($A$6:$A$35=A45)*$E$6:$E$35*$J$6:$J$35)/SUMIF($A$6:$A$35,A45,$E$6:$E$35),"") -> 0.54850612 | J45: =SUMIF($A$6:$A$35,A45,$N$6:$N$35) -> 2807500 | K45: =COUNTIFS($A$6:$A$35,A45,$K$6:$K$35,"Breach Risk")+COUNTIFS($A$6:$A$35,A45,$K$6:$K$35,"Monitoring") -> 2
A46: Q3 2024 | B46: 2024-09-30 | C46: =COUNTIF($A$6:$A$35,A46) -> 5 | D46: =SUMIF($A$6:$A$35,A46,$E$6:$E$35) -> 60250000 | E46: =SUMIF($A$6:$A$35,A46,$F$6:$F$35) -> 61850000 | F46: =SUMIF($A$6:$A$35,A46,$G$6:$G$35) -> 1600000 | G46: =IFERROR(SUMIF($A$6:$A$35,A46,$F$6:$F$35)/SUMIF($A$6:$A$35,A46,$E$6:$E$35),"") -> 1.026556 | H46: =IFERROR(SUMPRODUCT(($A$6:$A$35=A46)*($I$6:$I$35>0)*$E$6:$E$35*$I$6:$I$35)/SUMPRODUCT(($A$6:$A$35=A46)*($I$6:$I$35>0)*$E$6:$E$35),"") -> 1.8782158 | I46: =IFERROR(SUMPRODUCT(($A$6:$A$35=A46)*$E$6:$E$35*$J$6:$J$35)/SUMIF($A$6:$A$35,A46,$E$6:$E$35),"") -> 0.54653527 | J46: =SUMIF($A$6:$A$35,A46,$N$6:$N$35) -> 2792750 | K46: =COUNTIFS($A$6:$A$35,A46,$K$6:$K$35,"Breach Risk")+COUNTIFS($A$6:$A$35,A46,$K$6:$K$35,"Monitoring") -> 2
A47: Q4 2024 | B47: 2024-12-31 | C47: =COUNTIF($A$6:$A$35,A47) -> 5 | D47: =SUMIF($A$6:$A$35,A47,$E$6:$E$35) -> 59250000 | E47: =SUMIF($A$6:$A$35,A47,$F$6:$F$35) -> 60550000 | F47: =SUMIF($A$6:$A$35,A47,$G$6:$G$35) -> 1300000 | G47: =IFERROR(SUMIF($A$6:$A$35,A47,$F$6:$F$35)/SUMIF($A$6:$A$35,A47,$E$6:$E$35),"") -> 1.0219409 | H47: =IFERROR(SUMPRODUCT(($A$6:$A$35=A47)*($I$6:$I$35>0)*$E$6:$E$35*$I$6:$I$35)/SUMPRODUCT(($A$6:$A$35=A47)*($I$6:$I$35>0)*$E$6:$E$35),"") -> 1.8633333 | I47: =IFERROR(SUMPRODUCT(($A$6:$A$35=A47)*$E$6:$E$35*$J$6:$J$35)/SUMIF($A$6:$A$35,A47,$E$6:$E$35),"") -> 0.54834599 | J47: =SUMIF($A$6:$A$35,A47,$N$6:$N$35) -> 2779000 | K47: =COUNTIFS($A$6:$A$35,A47,$K$6:$K$35,"Breach Risk")+COUNTIFS($A$6:$A$35,A47,$K$6:$K$35,"Monitoring") -> 2
A48: Q1 2026 | B48: 2026-03-31 | C48: =COUNTIF($A$6:$A$35,A48) -> 5 | D48: =SUMIF($A$6:$A$35,A48,$E$6:$E$35) -> 62500000 | E48: =SUMIF($A$6:$A$35,A48,$F$6:$F$35) -> 64650000 | F48: =SUMIF($A$6:$A$35,A48,$G$6:$G$35) -> 2150000 | G48: =IFERROR(SUMIF($A$6:$A$35,A48,$F$6:$F$35)/SUMIF($A$6:$A$35,A48,$E$6:$E$35),"") -> 1.0344 | H48: =IFERROR(SUMPRODUCT(($A$6:$A$35=A48)*($I$6:$I$35>0)*$E$6:$E$35*$I$6:$I$35)/SUMPRODUCT(($A$6:$A$35=A48)*($I$6:$I$35>0)*$E$6:$E$35),"") -> 1.856 | I48: =IFERROR(SUMPRODUCT(($A$6:$A$35=A48)*$E$6:$E$35*$J$6:$J$35)/SUMIF($A$6:$A$35,A48,$E$6:$E$35),"") -> 0.55296 | J48: =SUMIF($A$6:$A$35,A48,$N$6:$N$35) -> 2917500 | K48: =COUNTIFS($A$6:$A$35,A48,$K$6:$K$35,"Breach Risk")+COUNTIFS($A$6:$A$35,A48,$K$6:$K$35,"Monitoring") -> 2
A52: C. Charts — Portfolio Fair Value & Unrealized G/L Time-Series
